{
  "title": "Completeness of death registration with cause-of-death information (%)",
  "name": "sp.reg.dths.zs",
  "worldbank": {
    "indicator": "sp.reg.dths.zs"
  },
  "readme": "Completeness of death registration is the estimated percentage of deaths that are registered with their cause of death information in the vital registration system of a country.",
  "licenses": [
    {
      "name": "CC-BY-4.0"
    }
  ],
  "keywords": [
    "Health "
  ],
  "resources": [
    {
      "name": "data",
      "title": "Indicator data",
      "path": "data.csv",
      "format": "csv",
      "mediatype": "text/csv",
      "encoding": "utf-8",
      "schema": {
        "fields": [
          {
            "name": "Country Name",
            "type": "string",
            "description": "Country or Region name"
          },
          {
            "name": "Country Code",
            "type": "string",
            "description": "ISO 3-digit ISO code extended to include regional codes e.g. EUR, ARB etc"
          },
          {
            "name": "Year",
            "type": "year",
            "description": "Year"
          },
          {
            "name": "Value",
            "type": "number",
            "description": "Completeness of death registration is the estimated percentage of deaths that are registered with their cause of death information in the vital registration system of a country."
          }
        ]
      }
    }
  ]
}